README.txt
setup.cfg
setup.py
auth_pubtkt/__init__.py
auth_pubtkt.egg-info/PKG-INFO
auth_pubtkt.egg-info/SOURCES.txt
auth_pubtkt.egg-info/dependency_links.txt
auth_pubtkt.egg-info/entry_points.txt
auth_pubtkt.egg-info/not-zip-safe
auth_pubtkt.egg-info/top_level.txt
auth_pubtkt/tests/__init__.py
auth_pubtkt/tests/tests.py
auth_pubtkt/tests/wsgiapp.py