Metadata-Version: 1.0
Name: auth-pubtkt
Version: 0.1
Summary: This software implements mod_auth_pubtkt authentication for Python world.
Home-page: https://github.com/AndreyPlotnikov/auth_pubtkt
Author: Andrey Plotnikov
Author-email: plotnikoff@gmail.com
License: BSD License
Keywords: mod_auth_pubtkt authentication single-sing-on
Platform: UNKNOWN
Classifier: Development Status :: 3 - Alpha
Classifier: Environment :: Web Environment
Classifier: Intended Audience :: Developers
Classifier: License :: OSI Approved :: BSD License
Classifier: Programming Language :: Python
Classifier: Topic :: Internet :: WWW/HTTP :: WSGI :: Middleware
